hcs_core/__init__.py
hcs_core/ctxp/__init__.py
hcs_core/ctxp/_init.py
hcs_core/ctxp/cli_options.py
hcs_core/ctxp/cli_processor.py
hcs_core/ctxp/cmd_util.py
hcs_core/ctxp/config.py
hcs_core/ctxp/context.py
hcs_core/ctxp/data_util.py
hcs_core/ctxp/dispatcher.py
hcs_core/ctxp/duration.py
hcs_core/ctxp/extension.py
hcs_core/ctxp/fn_util.py
hcs_core/ctxp/fstore.py
hcs_core/ctxp/jsondot.py
hcs_core/ctxp/logger.py
hcs_core/ctxp/profile.py
hcs_core/ctxp/profile_store.py
hcs_core/ctxp/recent.py
hcs_core/ctxp/state.py
hcs_core/ctxp/task_schd.py
hcs_core/ctxp/telemetry.py
hcs_core/ctxp/template_util.py
hcs_core/ctxp/timeutil.py
hcs_core/ctxp/util.py
hcs_core/ctxp/var_template.py
hcs_core/ctxp/built_in_cmds/__init__.py
hcs_core/ctxp/built_in_cmds/_ut.py
hcs_core/ctxp/built_in_cmds/context.py
hcs_core/ctxp/built_in_cmds/profile.py
hcs_core/plan/__init__.py
hcs_core/plan/actions.py
hcs_core/plan/base_provider.py
hcs_core/plan/context.py
hcs_core/plan/core.py
hcs_core/plan/dag.py
hcs_core/plan/helper.py
hcs_core/plan/kop.py
hcs_core/plan/provider/__init__.py
hcs_core/plan/provider/dev/__init__.py
hcs_core/plan/provider/dev/_prepare.py
hcs_core/plan/provider/dev/dummy.py
hcs_core/plan/provider/dev/fibonacci.py
hcs_core/sglib/__init__.py
hcs_core/sglib/auth.py
hcs_core/sglib/cli_options.py
hcs_core/sglib/client_util.py
hcs_core/sglib/csp.py
hcs_core/sglib/ez_client.py
hcs_core/sglib/hcs_client.py
hcs_core/sglib/init.py
hcs_core/sglib/login_support.py
hcs_core/sglib/payload_util.py
hcs_core/sglib/requtil.py
hcs_core/sglib/utils.py
hcs_core/util/__init__.py
hcs_core/util/check_license.py
hcs_core/util/duration.py
hcs_core/util/exit.py
hcs_core/util/hcs_constants.py
hcs_core/util/job_view.py
hcs_core/util/pki_util.py
hcs_core/util/query_util.py
hcs_core/util/scheduler.py
hcs_core/util/ssl_util.py
hcs_core/util/versions.py
hcs_core-0.1.321.dist-info/METADATA
hcs_core-0.1.321.dist-info/WHEEL
hcs_core-0.1.321.dist-info/RECORD
