Metadata-Version: 2.4
Name: hcs-core
Version: 0.1.321
Summary: Horizon Cloud Service CLI module.
Project-URL: Homepage, https://github.com/euc-eng/hcs-cli
Project-URL: Bug Tracker, https://github.com/euc-eng/hcs-cli/issues
Project-URL: documentation, https://readthedocs.org
Project-URL: repository, https://github.com/euc-eng/hcs-cli
Project-URL: changelog, https://github.com/euc-eng/hcs-cli/blob/main/CHANGELOG.md
Author-email: Nanw1103 <nanw1103@gmail.com>
Keywords: CLI,Horizon,Horizon Cloud,Horizon Cloud Service
Classifier: Development Status :: 3 - Alpha
Classifier: License :: OSI Approved :: MIT License
Classifier: Operating System :: OS Independent
Classifier: Programming Language :: Python :: 3
Requires-Python: >=3.9
Requires-Dist: authlib>=1.6.0
Requires-Dist: click>=8.1.8
Requires-Dist: coloredlogs>=15.0.1
Requires-Dist: cryptography>=45.0.5
Requires-Dist: graphviz>=0.21
Requires-Dist: httpx>=0.28.0
Requires-Dist: packaging>=25.0
Requires-Dist: portalocker>=3.0.0
Requires-Dist: psutil>=7.0.0
Requires-Dist: pydantic>=2.11.7
Requires-Dist: pyjwt>=2.10.1
Requires-Dist: pyopenssl>=25.1.0
Requires-Dist: python-dotenv>=1.1.1
Requires-Dist: pyyaml>=6.0.1
Requires-Dist: questionary>=2.0.1
Requires-Dist: rel>=0.4.9.20
Requires-Dist: retry>=0.9.2
Requires-Dist: rich>=14.0.0
Requires-Dist: schedule>=1.1.0
Requires-Dist: tabulate>=0.9.0
Requires-Dist: websocket-client>=1.2.3
Requires-Dist: yumako>=0.1.37
Provides-Extra: dev
Requires-Dist: bandit; extra == 'dev'
Requires-Dist: build; extra == 'dev'
Requires-Dist: flake8; extra == 'dev'
Requires-Dist: hatch; extra == 'dev'
Requires-Dist: mypy; extra == 'dev'
Requires-Dist: pylint; extra == 'dev'
Requires-Dist: pytest; extra == 'dev'
Requires-Dist: ruff; extra == 'dev'
Requires-Dist: twine; extra == 'dev'
Requires-Dist: vulture; extra == 'dev'
Requires-Dist: wheel; extra == 'dev'
Requires-Dist: yamlfix; extra == 'dev'
